spocktest/__init__.py
spocktest/defaults.py
spocktest/extract.py
spocktest/fixture.py
spocktest/inject.py
spocktest/main.py
spocktest/model.py
spocktest/state.py
spocktest/tools.py
tests/__init__.py
tests/test_cli.py
tests/test_get_snippet_code.py
tests/test_injection.py
tests/test_test_generation.py
spocktest-1.0.3.dist-info/LICENSE
spocktest-1.0.3.dist-info/METADATA
spocktest-1.0.3.dist-info/WHEEL
spocktest-1.0.3.dist-info/entry_points.txt
spocktest-1.0.3.dist-info/top_level.txt
spocktest-1.0.3.dist-info/RECORD
