Metadata-Version: 2.1
Name: spocktest
Version: 1.0.3
Summary: Embed unit test snippets into human-readable documentation
Home-page: UNKNOWN
Author: Krzysztof Czarnecki
Author-email: kjczarne@gmail.com
License: UNKNOWN
Platform: UNKNOWN
Requires-Dist: toolz
Requires-Dist: loguru
